[{"name":"Tømmeråsen","type":"ås","position":[-10992,6596251,101]},{"name":"Heståsen","type":"ås","position":[-15640,6596170,138]},{"name":"Lauvåsen","type":"ås","position":[-14664,6592679,51]},{"name":"Mjølsnesfjellet","type":"ås","position":[-22759,6597184,143]},{"name":"Vidås","type":"ås","position":[-16283,6596931,61]},{"name":"Aubøåsen","type":"ås","position":[-21155,6603882,80]},{"name":"Vetås","type":"ås","position":[-18876,6602042,108]},{"name":"Tjularåsen","type":"ås","position":[-22360,6603064,79]},{"name":"Sigmundstadåsen","type":"ås","position":[-11443,6591679,183]},{"name":"Helgøyåsen","type":"ås","position":[-21140,6601770,79]},{"name":"Lysåsen","type":"ås","position":[-10835,6592546,153]},{"name":"Borgaråsen","type":"ås","position":[-23350,6591763,48]},{"name":"Kallebakk","type":"ås","position":[-18359,6591466,158]},{"name":"Litle Randås","type":"ås","position":[-10956,6597682,304]},{"name":"Undelinuten","type":"fjell","position":[-11399,6602923,334]},{"name":"Varhaug","type":"ås","position":[-18778,6591595,144]},{"name":"Haråsen","type":"ås","position":[-22599,6596170,115]},{"name":"Høynes","type":"ås","position":[-20368,6596532,0]},{"name":"Hovdaåsen","type":"ås","position":[-11795,6596017,119]},{"name":"Kyrkjeberget","type":"fjell","position":[-11902,6595334,25]},{"name":"Lysåsen","type":"ås","position":[-15323,6595315,61]},{"name":"Husafjellet","type":"fjell","position":[-11545,6591340,110]},{"name":"Stumpen","type":"ås","position":[-11941,6598122,236]},{"name":"Havåsen","type":"ås","position":[-14159,6601343,177]},{"name":"Leidefjellet","type":"fjell","position":[-13560,6601460,205]},{"name":"Slettåsen","type":"ås","position":[-17945,6592684,61]},{"name":"Lauvåsen","type":"ås","position":[-16545,6597212,63]},{"name":"Hausen","type":"ås","position":[-22982,6591768,40]},{"name":"Kodnarkleivfjellet","type":"ås","position":[-22774,6596432,103]},{"name":"Litleåsen","type":"ås","position":[-21347,6601834,40]},{"name":"Åsadn","type":"ås","position":[-12696,6601932,192]},{"name":"Holefjellet","type":"fjell","position":[-15625,6601910,163]},{"name":"Trogedalsfjellet","type":"ås","position":[-11884,6602095,273]},{"name":"Hestås","type":"ås","position":[-16702,6593642,113]},{"name":"Bjørkåsen","type":"ås","position":[-11653,6598686,106]},{"name":"Ørnhus","type":"ås","position":[-11350,6601753,237]},{"name":"Skudefjellet","type":"fjell","position":[-13382,6594802,54]},{"name":"Storafjell","type":"ås","position":[-16943,6593599,125]},{"name":"Krogamyrane","type":"ås","position":[-12934,6603262,143]},{"name":"Bogskinnsfjellet","type":"fjell","position":[-15279,6602629,203]},{"name":"Sjøgningsåsen","type":"ås","position":[-10791,6598276,192]},{"name":"Skipet","type":"ås","position":[-14600,6600322,88]},{"name":"Varahei","type":"fjell","position":[-13301,6602228,260]},{"name":"Sjuråsen","type":"ås","position":[-12765,6601619,221]},{"name":"Myrafjellet","type":"fjell","position":[-15407,6601205,104]},{"name":"Linnåsen","type":"ås","position":[-16065,6596110,58]},{"name":"Nonsåsen","type":"ås","position":[-10829,6598389,154]},{"name":"Tappfjellet","type":"fjell","position":[-12440,6598528,107]},{"name":"Heståsen","type":"ås","position":[-12996,6594811,22]},{"name":"Almås","type":"ås","position":[-12308,6602624,278]},{"name":"Lausnesåsen","type":"ås","position":[-21262,6596201,97]},{"name":"Nonsås","type":"ås","position":[-14364,6600530,164]},{"name":"Randåsen","type":"ås","position":[-11189,6597828,371]},{"name":"Heianibbå","type":"fjell","position":[-11022,6597340,178]},{"name":"Knolten","type":"fjell","position":[-14731,6602541,246]},{"name":"Jomåsen","type":"ås","position":[-10811,6591560,228]},{"name":"Raunehagen","type":"ås","position":[-21380,6594835,146]},{"name":"Bjørnåsen","type":"ås","position":[-15871,6596462,94]},{"name":"Storafjellet","type":"fjell","position":[-16944,6593606,125]},{"name":"Kuhammar","type":"ås","position":[-23448,6593923,107]},{"name":"Trevlandsåsen","type":"ås","position":[-17919,6591956,93]},{"name":"Vestbøfjellet","type":"fjell","position":[-23498,6596032,121]},{"name":"Lauvåsen","type":"ås","position":[-14745,6601771,181]},{"name":"Vordnuten","type":"ås","position":[-14964,6602303,258]},{"name":"Nygardsheia","type":"ås","position":[-13411,6601269,191]},{"name":"Karifjellet","type":"fjell","position":[-13611,6602183,247]},{"name":"Medåsen","type":"ås","position":[-11569,6603687,248]},{"name":"Kårdalshaugen","type":"ås","position":[-12470,6601520,210]},{"name":"Sølbergsfjellet","type":"ås","position":[-15941,6603876,261]},{"name":"Sjydna","type":"ås","position":[-18711,6602022,89]}]