[{"name":"Lille Nuvsoaivi","type":"fjell","position":[1071365,7803105,139]},{"name":"Geresbákti","type":"ås","position":[1072381,7808946,98]},{"name":"Káren-Rávnnoaivi","type":"ås","position":[1072073,7806774,124]},{"name":"Hifjell","type":"fjell","position":[1067161,7804842,205]},{"name":"Gieddenjároaivi","type":"ås","position":[1064343,7810772,123]},{"name":"Simlefjellet","type":"fjell","position":[1064444,7803579,233]},{"name":"Kilfjellet","type":"fjell","position":[1061219,7809253,160]},{"name":"Náhteleioaivi","type":"ås","position":[1062346,7813794,140]},{"name":"Tusenvikfjellet","type":"fjell","position":[1067148,7805610,145]},{"name":"Kilefjellet","type":"ås","position":[1061042,7808864,178]},{"name":"Pulkfjellet","type":"ås","position":[1071441,7807993,79]},{"name":"Dápmotoaivi","type":"fjell","position":[1067167,7803203,235]},{"name":"Gáivvosoaivi","type":"ås","position":[1063677,7808401,97]},{"name":"Bealkurgáisá","type":"fjell","position":[1067915,7804084,203]},{"name":"Biipočohkka","type":"fjell","position":[1065492,7813874,83]},{"name":"Siiddoaivi","type":"ås","position":[1072722,7808251,122]},{"name":"Austre Nosfjellet","type":"ås","position":[1070501,7803545,211]},{"name":"Makkarapahta","type":"fjell","position":[1061985,7811649,79]},{"name":"Guolleveaibákti","type":"fjell","position":[1061005,7805917,89]},{"name":"Rivdnjoaivi","type":"ås","position":[1064180,7813401,127]},{"name":"Gárppoaivi","type":"fjell","position":[1064658,7812152,150]},{"name":"Storefjell","type":"fjell","position":[1067530,7813781,147]},{"name":"Vuolit Hearggoaivi","type":"fjell","position":[1062103,7802701,113]},{"name":"Dálasoaivi","type":"ås","position":[1072363,7805270,127]},{"name":"Hans Garmaroaivi","type":"fjell","position":[1068386,7806641,73]},{"name":"Toppen","type":"fjell","position":[1061350,7810599,173]}]