[{"name":"Nysetnatten","type":"ås","position":[183846,6748495,1232]},{"name":"Klantenatten","type":"ås","position":[188244,6745844,1099]},{"name":"Haugsjøfjellet","type":"ås","position":[190133,6755212,1068]},{"name":"Skuteknuten","type":"ås","position":[189381,6756069,1024]},{"name":"Rauddalsnatten","type":"ås","position":[190091,6745234,1081]},{"name":"Bergaleinnatten","type":"fjell","position":[188307,6748366,1111]},{"name":"Vestre Syningen","type":"ås","position":[189199,6749787,1099]},{"name":"Deildesnatten","type":"ås","position":[180595,6748821,1130]},{"name":"Vestre Sangeknatten","type":"ås","position":[190601,6753052,1098]},{"name":"Kvilingberget","type":"ås","position":[191124,6746070,1058]},{"name":"Skurveknatten","type":"ås","position":[187436,6750568,1156]},{"name":"Syningen","type":"ås","position":[188429,6750054,1141]},{"name":"Langehallfjellet","type":"ås","position":[188799,6751806,1172]},{"name":"Meitebekkfjellet","type":"ås","position":[186204,6750416,1219]},{"name":"Tangehøgdi","type":"ås","position":[186760,6755681,1012]},{"name":"Kvitåsen","type":"ås","position":[184162,6744749,1070]},{"name":"Raudskrinibbi","type":"ås","position":[183726,6751716,1185]},{"name":"Bufarknatten","type":"ås","position":[191061,6751525,1056]},{"name":"Miljomhaugen","type":"ås","position":[190513,6750628,985]},{"name":"Øytjernhøgde","type":"ås","position":[191534,6752580,1065]},{"name":"Falken","type":"ås","position":[185934,6752499,1183]},{"name":"Rauddalsfjellet","type":"fjell","position":[189501,6746832,1202]},{"name":"Rabalsfjellet","type":"ås","position":[190661,6748418,1155]},{"name":"Holtelifjellet","type":"fjell","position":[185316,6745072,1150]},{"name":"Hollastølsfjellet","type":"fjell","position":[188931,6751948,1174]},{"name":"Gamlestølfjellet","type":"ås","position":[189692,6751010,1085]},{"name":"Tempelhaugen","type":"ås","position":[193184,6749119,998]},{"name":"Haugsetfjellet","type":"ås","position":[188697,6754137,1148]},{"name":"Miljofjellet","type":"ås","position":[187918,6750042,1140]},{"name":"Nystølfjellet","type":"fjell","position":[183165,6749938,1272]},{"name":"Fiskebufjellet","type":"ås","position":[192450,6753521,1106]},{"name":"Søtehaugberget","type":"ås","position":[181357,6748097,1164]},{"name":"Endefjell","type":"ås","position":[182626,6748715,1186]},{"name":"Vesle Syningen","type":"ås","position":[189475,6750222,1100]},{"name":"Rauskreoberget","type":"ås","position":[189315,6751304,1088]},{"name":"Grevsjøfjellet","type":"ås","position":[189578,6748049,1146]},{"name":"Sangeknatten","type":"ås","position":[190362,6752720,1112]}]