[{"name":"Eggene","type":"fjell","position":[8798,6870727,782]},{"name":"Brendefjellet","type":"fjell","position":[10415,6859951,417]},{"name":"Åsane","type":"ås","position":[2184,6861974,160]},{"name":"Grønliheia","type":"ås","position":[2936,6863580,545]},{"name":"Hjortesetfjellet","type":"fjell","position":[10144,6870216,606]},{"name":"Høgefjellet","type":"fjell","position":[14472,6867802,363]},{"name":"Sletteheia","type":"fjell","position":[6677,6864043,774]},{"name":"Pikåsen","type":"ås","position":[5472,6865163,421]},{"name":"Setråsen","type":"ås","position":[6605,6868108,251]},{"name":"Vassbotnfjellet","type":"fjell","position":[3398,6860986,324]},{"name":"Blåfjellet","type":"fjell","position":[6823,6870122,623]},{"name":"Hestienden","type":"ås","position":[8250,6861439,569]},{"name":"Goddagsfjellet","type":"fjell","position":[12033,6870882,526]},{"name":"Høgefjellet","type":"fjell","position":[14154,6871242,352]},{"name":"Horstadåsen","type":"ås","position":[5724,6859120,470]},{"name":"Fitjeåsen","type":"ås","position":[11959,6861389,225]},{"name":"Tågebærhotten","type":"ås","position":[11153,6862826,513]},{"name":"Heia","type":"fjell","position":[6922,6862935,688]},{"name":"Endestadnipa","type":"fjell","position":[2220,6864839,760]},{"name":"Åsen","type":"ås","position":[8022,6866273,161]},{"name":"Eikåsen","type":"ås","position":[6677,6867293,269]},{"name":"Smylmedalsegga","type":"fjell","position":[12229,6865354,1113]},{"name":"Alliåsen","type":"ås","position":[7256,6867615,280]},{"name":"Hesteheia","type":"fjell","position":[8441,6861312,577]},{"name":"Søråsen","type":"ås","position":[4182,6868029,90]},{"name":"Kvitefjell","type":"fjell","position":[4082,6865339,458]},{"name":"Blåfjellet","type":"fjell","position":[6558,6870216,575]},{"name":"Lurelifjellet","type":"fjell","position":[11826,6870479,495]},{"name":"Eikåsfjellet","type":"fjell","position":[6655,6867335,260]},{"name":"Smylmedalsegga","type":"fjell","position":[12201,6865518,1024]},{"name":"Britelia","type":"ås","position":[7032,6870973,723]},{"name":"Urefjellet","type":"ås","position":[9362,6865769,512]},{"name":"Fuglåsen","type":"ås","position":[6012,6868568,263]},{"name":"Skogastovåsen","type":"ås","position":[6440,6867949,231]},{"name":"Middagsnova","type":"fjell","position":[14298,6866968,704]},{"name":"Kleivafjellet","type":"fjell","position":[14402,6861421,125]},{"name":"Nordlifjellet","type":"ås","position":[13630,6862783,547]},{"name":"Skathaugen","type":"ås","position":[14297,6860828,134]},{"name":"Branden","type":"ås","position":[4105,6867653,140]},{"name":"Nordåsen","type":"ås","position":[5314,6868664,272]},{"name":"Svarthumleheia","type":"fjell","position":[4234,6860113,565]},{"name":"Reineholten","type":"ås","position":[4896,6862045,339]},{"name":"Grøneliholten","type":"ås","position":[7128,6869356,444]},{"name":"Bjørkeneslægda","type":"ås","position":[9714,6866565,244]},{"name":"Åsane","type":"ås","position":[6753,6865866,218]},{"name":"Hjortesetfjellet","type":"ås","position":[11518,6871415,559]},{"name":"Kallandsåsen","type":"ås","position":[14486,6860049,477]},{"name":"Alnakken","type":"ås","position":[7960,6863333,880]},{"name":"Kvernhusholten","type":"ås","position":[5643,6861782,325]},{"name":"Tjørnaholten","type":"ås","position":[3023,6866972,152]},{"name":"Bugefjellet","type":"fjell","position":[4367,6869686,277]},{"name":"Bjørnafjellet","type":"fjell","position":[3868,6861012,420]},{"name":"Lindåsen","type":"ås","position":[5760,6867593,143]},{"name":"Vassendenova","type":"ås","position":[9389,6865653,564]},{"name":"Amliåsen","type":"ås","position":[7208,6867594,283]},{"name":"Storefjellet","type":"fjell","position":[4903,6859842,539]},{"name":"Blåfjellet","type":"fjell","position":[4568,6864330,598]},{"name":"Ørneklumpen","type":"ås","position":[5187,6863083,633]},{"name":"Bjørnaholten","type":"ås","position":[4307,6861090,397]},{"name":"Urafjellet","type":"fjell","position":[3126,6862205,267]},{"name":"Skolten","type":"ås","position":[9051,6859375,405]},{"name":"Høgefjellet","type":"fjell","position":[11804,6860921,136]},{"name":"Høgenipa","type":"ås","position":[9311,6862386,549]},{"name":"Bugefjellet","type":"fjell","position":[4868,6869575,237]},{"name":"Dyretoppen","type":"ås","position":[8048,6860552,635]},{"name":"Grøneknausen","type":"ås","position":[14440,6866349,797]},{"name":"Snipphamrane","type":"ås","position":[10135,6862649,430]},{"name":"Boltholmhaugen","type":"ås","position":[2930,6867398,129]},{"name":"Skredryggen","type":"ås","position":[2120,6871555,605]},{"name":"Knausen","type":"ås","position":[4640,6870401,695]}]