[{"name":"Korstadkampen","type":"ås","position":[247259.04,6819270.82]},{"name":"Vardberget","type":"ås","position":[244508.2,6820718.57]},{"name":"Steinåsen","type":"ås","position":[256599.64,6812161.93]},{"name":"Vakkeråsen","type":"ås","position":[256565.45,6811398.26]},{"name":"Stulsfjellet","type":"ås","position":[250412.66,6819748.95]},{"name":"Varpåsen","type":"ås","position":[253085.94,6810204.78]},{"name":"Hjellhøgda","type":"ås","position":[250051.53,6818373.83]},{"name":"Djupdalskampen","type":"ås","position":[249425.09,6820005.45]},{"name":"Bakkeberget","type":"ås","position":[244846.94,6820288.12]},{"name":"Stenumgardshøgda","type":"ås","position":[251271.25,6818230.06]},{"name":"Svartåsen","type":"ås","position":[256640.99,6816503.41]},{"name":"Leirdalskampen","type":"ås","position":[247031.03,6818190.8]},{"name":"Svangkampen","type":"ås","position":[251414.52,6818909.62]}]