[{"name":"Vetaåsen","type":"ås","position":[268845,6587096,110]},{"name":"Vardås","type":"ås","position":[261696,6591109,57]},{"name":"Solbergfjellet","type":"ås","position":[261327,6579658,68]},{"name":"Vardås","type":"ås","position":[260638,6584589,44]},{"name":"Solbergåsen","type":"ås","position":[261571,6580626,75]},{"name":"Partlefjellet","type":"ås","position":[264215,6578959,70]},{"name":"Varden","type":"ås","position":[262770,6585974,57]},{"name":"Østre Åsen","type":"ås","position":[259074,6584244,27]},{"name":"Ravneberg","type":"ås","position":[262733,6579871,95]},{"name":"Fugleleiken","type":"ås","position":[262072,6590455,61]},{"name":"Ælinåsen","type":"ås","position":[267325,6580926,60]},{"name":"Høyås","type":"ås","position":[269116,6584157,68]},{"name":"Høyumfjellet","type":"ås","position":[267154,6579583,68]},{"name":"Fugleleiken","type":"ås","position":[267507,6587295,83]},{"name":"Ridefjell","type":"ås","position":[268994,6586642,90]},{"name":"Vestre Åsen","type":"ås","position":[258619,6583976,27]},{"name":"Tuggeliteåsen","type":"ås","position":[259099,6586797,20]},{"name":"Rørfjell","type":"ås","position":[262729,6580637,114]},{"name":"Burås","type":"ås","position":[265083,6580000,77]},{"name":"Langklo","type":"ås","position":[269648,6587973,120]},{"name":"Ravneberget","type":"ås","position":[266605,6581339,43]},{"name":"Røsåberget","type":"ås","position":[264389,6580059,91]},{"name":"Bunnåsen","type":"ås","position":[268537,6586773,82]},{"name":"Strømnesfjellet","type":"ås","position":[264232,6585162,60]}]