[{"name":"Skarven","type":"ås","position":[296880.9,6892194.53]},{"name":"Svarthammaren","type":"ås","position":[297217.11,6893997.8]},{"name":"Vollskampen","type":"ås","position":[295720.94,6885920.83]},{"name":"Nekkjølen","type":"ås","position":[302325.34,6891710.19]},{"name":"Kusten","type":"ås","position":[306329.09,6894972.18]},{"name":"Langkletten","type":"ås","position":[296241.57,6890610.23]},{"name":"Fellingåsen","type":"ås","position":[297488.32,6885340.71]},{"name":"Klettsæterklettan","type":"fjell","position":[297730.15,6887522.48]},{"name":"Brennkletten","type":"ås","position":[302786.3,6887369.71]},{"name":"Nekvollåsen","type":"ås","position":[295880.29,6887724.48]},{"name":"Slettfjellet","type":"ås","position":[297818.31,6894454.57]},{"name":"Utistukletten","type":"ås","position":[304700.74,6893782.19]},{"name":"Engåsen","type":"ås","position":[296845.44,6884993.39]},{"name":"Gråfjellet","type":"ås","position":[303017.58,6885141.05]},{"name":"Gloppa","type":"ås","position":[300227.82,6886451.71]}]