[{"name":"Grasliberget","type":"ås","position":[300931,6827706,670]},{"name":"Målbekkhammaren","type":"ås","position":[301481,6826232,670]},{"name":"Søre Røstet","type":"ås","position":[303708,6824233,637]},{"name":"Veksenbekkåsen","type":"ås","position":[307834,6831297,709]},{"name":"Skramsliberget","type":"ås","position":[301646,6827493,736]},{"name":"Andråsberget","type":"ås","position":[301364,6831473,763]},{"name":"Storåsen","type":"ås","position":[295486,6828664,809]},{"name":"Andtjønnkletten","type":"ås","position":[303432,6830912,746]},{"name":"Veksenvola","type":"ås","position":[305187,6831439,804]},{"name":"Nordre Røstet","type":"ås","position":[302780,6825661,670]},{"name":"Nysæteråsen","type":"ås","position":[307582,6821145,821]}]