[{"name":"Grønberget","type":"ås","position":[361809.99,6807446.65]},{"name":"Skardtuppegga","type":"ås","position":[359924.58,6806645.03]},{"name":"Skjærhollfjellet","type":"ås","position":[368116.33,6805454.24]},{"name":"Granåsen","type":"ås","position":[371705.15,6804269.11]},{"name":"Rømholen","type":"ås","position":[359135,6798275.39]},{"name":"Bjørnåsen","type":"ås","position":[363047.67,6796025.92]},{"name":"Storgnollen","type":"ås","position":[362755.99,6805183.55]},{"name":"Tektgnollen","type":"ås","position":[370936.75,6806185.33]},{"name":"Granåsen","type":"ås","position":[359722.34,6800360.45]},{"name":"Storstenåsen","type":"ås","position":[360908.89,6798712.94]},{"name":"Grønberget","type":"fjell","position":[364380.75,6804879.66]},{"name":"Styggbekkåsen","type":"ås","position":[364728.52,6797450.29]},{"name":"Kanka","type":"ås","position":[365487.26,6803486.47]},{"name":"Granåsen","type":"ås","position":[359682.99,6800274.06]},{"name":"Ryskåsen","type":"ås","position":[362139.54,6800693.54]},{"name":"Buåsen","type":"ås","position":[360882.33,6799427]},{"name":"Hakkspetthøgda","type":"ås","position":[365702.92,6797740.11]},{"name":"Volfjellet","type":"fjell","position":[366221.93,6807260.58]},{"name":"Høa","type":"ås","position":[369781.24,6804901.55]}]