[{"name":"Flæheinuten","type":"ås","position":[50755.29,6627060.47]},{"name":"Hyttinghaugane","type":"ås","position":[51930.25,6627654.32]},{"name":"Skoranutane","type":"fjell","position":[44796.24,6628550.86]},{"name":"Krossvatn","type":"turisthytte","position":[41777.67,6619871.43]},{"name":"Skorpa","type":"fjell","position":[44860.86,6618151.2]},{"name":"Flæheii","type":"ås","position":[50059.21,6628484.39]},{"name":"Hovassribbane","type":"ås","position":[50284.54,6620762.95]},{"name":"Litlafjellet","type":"ås","position":[42902.85,6621379.6]},{"name":"Kaldafjellet","type":"fjell","position":[46985.35,6625730.98]},{"name":"Soksetangen","type":"ås","position":[50587.35,6619285.13]},{"name":"Nedre Leirnuten","type":"ås","position":[40979.95,6622605.51]},{"name":"Steinkilenuten","type":"ås","position":[44859.24,6624106.52]},{"name":"Kaldefjødd","type":"fjell","position":[46977.05,6625782.9]},{"name":"Snønuten","type":"fjell","position":[40422.61,6626225.21]},{"name":"Nonsnuten","type":"ås","position":[41671.29,6628366.42]},{"name":"Leirnuten","type":"fjell","position":[43052.61,6623086.85]},{"name":"Rishovd","type":"ås","position":[50026.95,6629072.08]},{"name":"Grønafjellet","type":"ås","position":[45733.12,6620156.96]},{"name":"Sandbankane","type":"fjell","position":[51471.91,6623266.57]},{"name":"Svonuten","type":"ås","position":[50440.05,6625648.88]}]