[{"name":"Kvigtindaksla","type":"fjell","position":[443739.89,7232456.96]},{"name":"Voenjelensnjurhtjie","type":"fjell","position":[443653.39,7234202.89]},{"name":"Bissietjahke","type":"fjell","position":[439873.62,7235856.81]},{"name":"Kråhtjoehtjahke","type":"fjell","position":[438819.62,7231963.98]},{"name":"Moevstjahke","type":"fjell","position":[442009,7238263.14]},{"name":"Måsskardfjellet","type":"fjell","position":[442879.82,7235499.75]},{"name":"Simskardhytta","type":"turisthytte","position":[437445.94,7240905.76]},{"name":"Gilmehtje","type":"ås","position":[447355.17,7237594.2]},{"name":"Rørskardtinden","type":"fjell","position":[438187.77,7235235.17]},{"name":"Gaksfjellet","type":"fjell","position":[437774.38,7229375.93]},{"name":"Rørskardaksla","type":"fjell","position":[435696.26,7232240]}]