[{"name":"Tverrfjellet","type":"ås","position":[472799,7567384,303]},{"name":"Budalstinden","type":"ås","position":[468847,7563656,641]},{"name":"Jotinden","type":"fjell","position":[472374,7572412,560]},{"name":"Lilletinden","type":"ås","position":[465155,7571917,177]},{"name":"Litlhåtinden","type":"ås","position":[461899,7569966,484]},{"name":"Strandås","type":"ås","position":[469331,7569650,20]},{"name":"Kotaksla","type":"ås","position":[461275,7569451,479]},{"name":"Småkallan","type":"ås","position":[471943,7564602,362]},{"name":"Breitinden","type":"ås","position":[470944,7564856,547]},{"name":"Breitinden","type":"fjell","position":[472408,7568200,615]},{"name":"Nonstindan","type":"ås","position":[470901,7567884,542]},{"name":"Nordåsen","type":"ås","position":[473538,7565861,112]},{"name":"Kjerringfjellet","type":"fjell","position":[469038,7562214,83]},{"name":"Tretindan","type":"ås","position":[470403,7568021,585]},{"name":"Hopsåsen","type":"ås","position":[473562,7565491,72]},{"name":"Smorttinden","type":"ås","position":[464634,7572128,518]},{"name":"Nordfjellet","type":"fjell","position":[468787,7567000,597]},{"name":"Trolldalsheia","type":"ås","position":[468913,7562959,393]},{"name":"Kvanndalstinden","type":"ås","position":[469573,7563517,775]},{"name":"Stortuva","type":"ås","position":[473496,7572694,390]},{"name":"Lyngværfjellet","type":"fjell","position":[471181,7568618,393]},{"name":"Smortaksla","type":"ås","position":[464648,7572645,390]},{"name":"Kollan","type":"ås","position":[471827,7571586,167]},{"name":"Sørfjellet","type":"fjell","position":[469602,7565865,209]},{"name":"Piggåsen","type":"ås","position":[473353,7564865,75]},{"name":"Søråsen","type":"ås","position":[473632,7565180,122]},{"name":"Hesten og mannen","type":"ås","position":[472674,7567903,431]},{"name":"Lågheia","type":"ås","position":[463188,7572884,171]},{"name":"Håtinden","type":"fjell","position":[461989,7570890,645]},{"name":"Varden","type":"ås","position":[463137,7567087,74]},{"name":"Varden","type":"ås","position":[464007,7571940,579]},{"name":"Håtindryggen","type":"ås","position":[462320,7571170,507]},{"name":"Småtindan","type":"fjell","position":[471004,7567949,552]},{"name":"Skakktinden","type":"ås","position":[471396,7568265,517]},{"name":"Malnesheia","type":"ås","position":[463306,7568141,93]},{"name":"Smånubban","type":"ås","position":[472671,7572672,367]},{"name":"Kvasstinden","type":"ås","position":[472671,7572467,482]},{"name":"Åmunddalskollen","type":"ås","position":[471599,7568039,431]},{"name":"Malnesåsen","type":"ås","position":[463386,7568427,100]},{"name":"Kjerringa","type":"ås","position":[471566,7564781,483]},{"name":"Sørfjellet","type":"ås","position":[468229,7565057,352]},{"name":"Glomtinden","type":"ås","position":[471426,7565704,382]},{"name":"Lyngværfjellet","type":"fjell","position":[468811,7567814,623]},{"name":"Vågakallen","type":"fjell","position":[470803,7564091,906]},{"name":"Høgtinden","type":"ås","position":[470239,7568052,688]},{"name":"Skredtinden","type":"ås","position":[468766,7568266,429]},{"name":"Skimtet","type":"ås","position":[462892,7571501,441]},{"name":"Nubban","type":"ås","position":[463409,7571019,322]},{"name":"Anderstinden","type":"ås","position":[464448,7571907,527]},{"name":"Vikjordtinden","type":"fjell","position":[461785,7569636,589]},{"name":"Tverråsen","type":"ås","position":[464070,7572734,201]},{"name":"Åttlitinden","type":"ås","position":[462998,7570438,338]},{"name":"Festvågtinden","type":"ås","position":[467867,7562922,528]},{"name":"Åsen","type":"ås","position":[469097,7569509,25]},{"name":"Kleppstadheia","type":"ås","position":[471558,7572905,507]},{"name":"Omntinden","type":"ås","position":[472212,7569045,434]},{"name":"Kallebordet","type":"ås","position":[471365,7564778,412]},{"name":"Forsdalsfloget","type":"fjell","position":[463351,7570558,148]}]