[{"name":"Småflotten","type":"fjell","position":[485343,7604872,426]},{"name":"Kristianlitinden","type":"fjell","position":[485551,7604784,441]},{"name":"Finnsæterkollen","type":"ås","position":[485298,7605294,413]},{"name":"Mårsundfjellet","type":"ås","position":[480295,7611065,105]},{"name":"Linfjellet","type":"fjell","position":[486325,7606952,92]},{"name":"Durmålstindan","type":"ås","position":[486280,7604094,550]},{"name":"Taennyken","type":"fjell","position":[485602,7604879,550]},{"name":"Galdertinden","type":"fjell","position":[485755,7604595,330]},{"name":"Middagstinden","type":"ås","position":[486050,7605290,413]},{"name":"Årnakkan","type":"ås","position":[485954,7606172,45]},{"name":"Kulitinden","type":"fjell","position":[485978,7604271,318]},{"name":"Sørennipa","type":"ås","position":[485163,7605018,428]},{"name":"Vindhamran","type":"ås","position":[478493,7611067,15]},{"name":"Slottfjellet","type":"fjell","position":[485377,7605829,212]},{"name":"Åsen","type":"ås","position":[485601,7606700,66]},{"name":"Steineklubben","type":"ås","position":[479277,7611187,85]}]