[{"name":"Silldevárre","type":"ås","position":[501060,7430506,691]},{"name":"Inner-Åsen","type":"ås","position":[511872,7422681,321]},{"name":"Littj-Skjevlfjellet","type":"fjell","position":[509865,7429913,645]},{"name":"Littj Skjevlfjellet","type":"ås","position":[510507,7431688,559]},{"name":"Skjevlfjellet","type":"fjell","position":[506780,7430025,669]},{"name":"Reinosthellaren","type":"ås","position":[507434,7432110,545]},{"name":"Varden","type":"ås","position":[505250,7432289,702]},{"name":"Gåsvassryggen","type":"fjell","position":[501495,7426279,654]},{"name":"Oksvassheia","type":"ås","position":[500983,7423537,705]},{"name":"Jervhiet","type":"ås","position":[504408,7428758,491]},{"name":"Tverråsen","type":"ås","position":[503327,7428363,451]},{"name":"Gamdalsfjellet","type":"fjell","position":[500290,7420708,897]},{"name":"Gåsvassryggen","type":"ås","position":[501848,7428457,580]},{"name":"Stabburdalhøgda","type":"ås","position":[499889,7427360,720]},{"name":"Jordbruhytta","type":"turisthytte","position":[510355,7424258,327]},{"name":"Djupdalsryggen","type":"ås","position":[502496,7425766,592]},{"name":"Langvasskogen","type":"ås","position":[502083,7428407,536]}]