[{"name":"Fisketindan","type":"ås","position":[516279.95,7603411.62]},{"name":"Høgfjelltinden","type":"ås","position":[515927.46,7600567.94]},{"name":"Vasstinden","type":"ås","position":[517092.42,7606800.77]},{"name":"Møysalaksla","type":"ås","position":[517318.56,7603170.47]},{"name":"Vangpollheia","type":"ås","position":[524710.21,7610207.53]},{"name":"Heia","type":"ås","position":[516501.96,7610062.9]},{"name":"Rødhatten","type":"fjell","position":[512082.99,7600050.99]},{"name":"Middagstinden","type":"ås","position":[512567.54,7604676.28]},{"name":"Møyen","type":"ås","position":[518549.05,7601332.96]},{"name":"Åsan","type":"ås","position":[514008.96,7605850.01]},{"name":"Mellaslottfjellet","type":"fjell","position":[518002.05,7608834]},{"name":"Fuglen","type":"ås","position":[515023.53,7607336.37]},{"name":"Breidtinden","type":"ås","position":[523888.32,7607758.22]},{"name":"Kløfttinden","type":"fjell","position":[519230.64,7608050.21]},{"name":"Nordtinden","type":"fjell","position":[522278.81,7603836.75]},{"name":"Åneheia","type":"ås","position":[521218.41,7609168.89]},{"name":"Rødsandheia","type":"ås","position":[514280.07,7607639.27]},{"name":"Raptinden","type":"ås","position":[513566.34,7600405.13]},{"name":"Kaljordtinden","type":"fjell","position":[512708.27,7601116.73]},{"name":"Setfjellet","type":"ås","position":[512332.98,7599666.91]},{"name":"Kvanntoheia","type":"ås","position":[516128.41,7601647.52]},{"name":"Kammen","type":"fjell","position":[519902.09,7606069.15]},{"name":"Forselvheia","type":"ås","position":[521530.22,7599488.73]},{"name":"Møysalen","type":"fjell","position":[518468.52,7601574.27]},{"name":"Forselvtinden","type":"fjell","position":[520504.55,7599727.64]},{"name":"Tretinden","type":"ås","position":[514476.67,7603029.84]},{"name":"Klubben","type":"ås","position":[517984.99,7607188.91]},{"name":"Aksla","type":"ås","position":[514386.02,7605232.08]},{"name":"Middagsvassaksla","type":"ås","position":[513996.05,7604506.05]},{"name":"Durmålsheia","type":"ås","position":[518299.97,7609195.13]},{"name":"Hellarlitinden","type":"fjell","position":[514546.03,7606601.05]},{"name":"Djupfjordtindan","type":"fjell","position":[522486.62,7609981.54]},{"name":"Trivassryggen","type":"ås","position":[521226.74,7605211.52]},{"name":"Memurutinden","type":"ås","position":[516708.51,7600864.77]},{"name":"Småvasstindan","type":"ås","position":[513739.16,7603393.03]},{"name":"Raudtinden","type":"fjell","position":[520038.16,7603026.83]},{"name":"Blokktindan","type":"fjell","position":[517133.39,7606173.24]},{"name":"Totinden","type":"ås","position":[515446.95,7602552.45]},{"name":"Vestpolltinden","type":"fjell","position":[524646.42,7600300.31]},{"name":"Middagstinden","type":"ås","position":[516172.71,7607661.91]},{"name":"Grøntinden","type":"ås","position":[518463.08,7603673.87]},{"name":"Kjerketinden","type":"ås","position":[514580.69,7600932.38]},{"name":"Steinheia","type":"ås","position":[517629.98,7609702.93]},{"name":"Snytindhytta","type":"turisthytte","position":[523473.83,7605860.28]}]