[{"name":"Varden","type":"ås","position":[618727.17,7596029.45]},{"name":"Gáicačorru","type":"ås","position":[621393.57,7587063.49]},{"name":"Sládjočohkka","type":"fjell","position":[625590.28,7588079.2]},{"name":"Haugfjell","type":"fjell","position":[618734.94,7596026.71]},{"name":"Ruoidnačohkka","type":"fjell","position":[618533.55,7587898.64]},{"name":"Ruoidnanjunni","type":"fjell","position":[615431.67,7589216.41]},{"name":"Bjørnfjell","type":"fjell","position":[626579.99,7596107.12]},{"name":"Lille Rundtinden","type":"fjell","position":[624704.34,7597878]},{"name":"Kalveholsfjellet","type":"fjell","position":[621766.59,7590608.16]},{"name":"Katterat fjellstue","type":"turisthytte","position":[621896.81,7590196.69]},{"name":"Hunddalstoppen","type":"ås","position":[621229.49,7589007.54]},{"name":"Sørdalstinden","type":"ås","position":[623371.72,7586710.95]},{"name":"Katterat","type":"fjell","position":[625182.26,7592163.53]},{"name":"Middagselvfjellet","type":"fjell","position":[618695.06,7590139.9]},{"name":"Spionkopen","type":"ås","position":[624080.01,7593947.08]},{"name":"Gátternjunni","type":"ås","position":[626214.43,7593053.56]},{"name":"Lille Haugfjell","type":"fjell","position":[623168.96,7596846.94]},{"name":"Tappelvfjellet","type":"fjell","position":[621003.98,7589381.61]},{"name":"Store Haugfjell","type":"fjell","position":[617985.05,7595126.95]},{"name":"Vokterboligen","type":"turisthytte","position":[622592.96,7590904.58]},{"name":"Trongdalsfjellet","type":"fjell","position":[621801.01,7592292.89]},{"name":"Grensefjellet","type":"fjell","position":[626086.73,7593084.4]}]