[{"name":"Muvravárseaibbuš","type":"fjell","position":[853094,7828878,457]},{"name":"Ulveryggen","type":"fjell","position":[843566,7840351,523]},{"name":"Muvravárri","type":"fjell","position":[855262,7831231,525]},{"name":"Ánddeš-Bierčohkat","type":"fjell","position":[852125,7832177,404]},{"name":"Guovžavárri","type":"fjell","position":[851706,7833604,437]},{"name":"Oaivvoščopma","type":"fjell","position":[854384,7835107,344]},{"name":"Laššesvárri","type":"fjell","position":[852068,7840412,350]},{"name":"Ráhpesvárri","type":"fjell","position":[849416,7829593,429]},{"name":"Geaidnočohkka","type":"fjell","position":[845125,7836133,567]},{"name":"Svartfjellet","type":"fjell","position":[852390,7840188,325]},{"name":"Ráktooaivvit","type":"fjell","position":[855735,7830025,450]},{"name":"Luoktabogevárri","type":"fjell","position":[855407,7839449,357]},{"name":"Svartfjellet","type":"fjell","position":[850650,7837694,411]},{"name":"Buikočohkat","type":"ås","position":[850967,7830030,424]},{"name":"Viroš","type":"fjell","position":[850172,7835784,472]},{"name":"Ruksesbávtterášša","type":"fjell","position":[848014,7838930,514]},{"name":"Breidalsfjellet","type":"fjell","position":[847060,7832004,468]},{"name":"Breidalsfjellet","type":"fjell","position":[846908,7834698,510]}]